django_easy_response-1.0.2.dist-info/DESCRIPTION.rst
django_easy_response-1.0.2.dist-info/METADATA
django_easy_response-1.0.2.dist-info/metadata.json
django_easy_response-1.0.2.dist-info/RECORD
django_easy_response-1.0.2.dist-info/top_level.txt
django_easy_response-1.0.2.dist-info/WHEEL
easy_response/__init__.py
easy_response/consts.py
easy_response/decorators.py
easy_response/http.py
easy_response/middleware.py
easy_response/status.py
easy_response/utils/__init__.py
easy_response/utils/process.py
easy_response/utils/serialize.py
