Metadata-Version: 2.0
Name: django-easy-response
Version: 1.0.2
Summary: Return HTTP responses in a easier way
Home-page: https://github.com/laginha/django-easy-response
Author: Diogo Laginha
Author-email: diogo.laginha.machado@gmail.com
License: MIT
Platform: UNKNOWN
Classifier: License :: OSI Approved :: MIT License
Classifier: Programming Language :: Python :: 2
Classifier: Intended Audience :: Developers
Requires-Dist: django
